jjrawlins_cdk_git_tagger/__init__.py
jjrawlins_cdk_git_tagger/py.typed
jjrawlins_cdk_git_tagger/_jsii/__init__.py
jjrawlins_cdk_git_tagger/_jsii/cdk-git-tagger@0.0.115.jsii.tgz
jjrawlins_cdk_git_tagger-0.0.115.dist-info/LICENSE
jjrawlins_cdk_git_tagger-0.0.115.dist-info/METADATA
jjrawlins_cdk_git_tagger-0.0.115.dist-info/WHEEL
jjrawlins_cdk_git_tagger-0.0.115.dist-info/top_level.txt
jjrawlins_cdk_git_tagger-0.0.115.dist-info/RECORD
